cannoli/__init__.py
cannoli/cannoli.py
cannoli/default_settings.json
cannoli/datasets/reviews.dsv
cannoli/utils/generate_dataset.py
cannoli/utils/generate_test_dataset.py
cannoli-0.1.27.dist-info/LICENSE
cannoli-0.1.27.dist-info/METADATA
cannoli-0.1.27.dist-info/WHEEL
cannoli-0.1.27.dist-info/top_level.txt
cannoli-0.1.27.dist-info/RECORD
