Metadata-Version: 2.1
Name: cannoli
Version: 0.1.27
Summary: Lib for prompt engineering using OpenAI
Home-page: https://github.com/naruminho/cannoli
Author: Narumi Abe, Bruna Luzzi
Author-email: mail.narumi@gmail.com
Classifier: Programming Language :: Python :: 3
Classifier: License :: OSI Approved :: MIT License
Classifier: Operating System :: OS Independent
License-File: LICENSE
Requires-Dist: openai ==0.28.1
Requires-Dist: pandas
Requires-Dist: openpyxl
